funtool_scratch_processes/__init__.py
funtool_scratch_processes/adaptors/__init__.py
funtool_scratch_processes/adaptors/autosave_directory.py
funtool_scratch_processes/analysis_selectors/__init__.py
funtool_scratch_processes/analysis_selectors/default.py
funtool_scratch_processes/group_measures/__init__.py
funtool_scratch_processes/group_measures/default.py
funtool_scratch_processes/grouping_selectors/__init__.py
funtool_scratch_processes/grouping_selectors/default.py
funtool_scratch_processes/reporters/__init__.py
funtool_scratch_processes/reporters/sampling_reporters.py
funtool_scratch_processes/reporters/save_group_info_to_file.py
funtool_scratch_processes/reporters/save_groups_to_file.py
funtool_scratch_processes/reporters/save_states_to_file.py
funtool_scratch_processes/reporters/to_repl.py
funtool_scratch_processes/state_measures/__init__.py
funtool_scratch_processes/state_measures/default.py
funtool_scratch_processes/state_measures/search_for_blocks.py
funtool_scratch_processes/state_measures/shared.py
funtool_scratch_processes-0.0.42.dist-info/DESCRIPTION.rst
funtool_scratch_processes-0.0.42.dist-info/METADATA
funtool_scratch_processes-0.0.42.dist-info/metadata.json
funtool_scratch_processes-0.0.42.dist-info/RECORD
funtool_scratch_processes-0.0.42.dist-info/top_level.txt
funtool_scratch_processes-0.0.42.dist-info/WHEEL
