Metadata-Version: 2.0
Name: funtool-scratch-processes
Version: 0.0.42
Summary: process to be used with the FUN Tool to analyze Scratch projects
Home-page: UNKNOWN
Author: Active Learning Lab
Author-email: pjanisiewicz@gmail.com
License: MIT
Platform: UNKNOWN
Classifier: Development Status :: 3 - Alpha
Classifier: Intended Audience :: Developers
Classifier: License :: OSI Approved :: MIT License
Classifier: Programming Language :: Python :: 3
Classifier: Programming Language :: Python :: 3.2
Classifier: Programming Language :: Python :: 3.3
Classifier: Programming Language :: Python :: 3.4
Requires-Dist: funtool
Requires-Dist: chardet
